unit_hifigan/__init__.py
unit_hifigan/compatibility.py
unit_hifigan/data.py
unit_hifigan/inference.py
unit_hifigan/loss.py
unit_hifigan/model.py
unit_hifigan/py.typed
unit_hifigan/train.py
unit_hifigan/utils.py
unit_hifigan/wer/__init__.py
unit_hifigan/wer/torchaudio.py
unit_hifigan/wer/whisper.py
unit_hifigan-0.1.2.dist-info/licenses/LICENSE
unit_hifigan-0.1.2.dist-info/WHEEL
unit_hifigan-0.1.2.dist-info/METADATA
unit_hifigan-0.1.2.dist-info/RECORD
