Metadata-Version: 2.4
Name: unit-hifigan
Version: 0.1.2
Summary: Unit HiFi-GAN
Author: Maxime Poli
Author-email: CoML <dev@cognitive-ml.fr>
Requires-Python: >=3.13
License-Expression: MIT
License-File: LICENSE
Requires-Dist: huggingface-hub>=0.35.3
Requires-Dist: numpy>=2.3.3
Requires-Dist: polars>=1.33.1
Requires-Dist: safetensors>=0.6.2
Requires-Dist: torch>=2.8.0
Requires-Dist: torchaudio>=2.8.0
Requires-Dist: torchcodec>=0.7.0
Requires-Dist: torchdata>=0.11.0
Requires-Dist: tqdm>=4.67.1
Requires-Dist: viztracer>=1.0.4
Requires-Dist: openai-whisper>=20250625 ; extra == "whisper"
Provides-Extra: whisper
